circomlibpy/__init__.py
circomlibpy/merkle_tree.py
circomlibpy/poseidon.py
circomlibpy/poseidon_constants.py
circomlibpy-1.0.0.dist-info/LICENSE
circomlibpy-1.0.0.dist-info/METADATA
circomlibpy-1.0.0.dist-info/WHEEL
circomlibpy-1.0.0.dist-info/top_level.txt
circomlibpy-1.0.0.dist-info/RECORD
