Metadata-Version: 2.1
Name: circomlibpy
Version: 1.0.0
Summary: Circom libs in Python
Author-email: Artem Belozerov <hoongun.off@yandex.ru>
License: MIT License
Project-URL: Repository, https://github.com/hoongun/circomlibjs.git
Keywords: poseidon,merkle,circom,zkp,zero-knowledge
Classifier: Development Status :: 5 - Production/Stable
Classifier: Environment :: Console
Classifier: Framework :: Jupyter
Classifier: Intended Audience :: Developers
Classifier: Intended Audience :: Education
Classifier: Intended Audience :: Science/Research
Classifier: License :: OSI Approved :: GNU General Public License (GPL)
Classifier: Operating System :: OS Independent
Classifier: Programming Language :: Python :: 3
Classifier: Programming Language :: Python :: 3.10
Classifier: Programming Language :: Python :: 3.11
Classifier: Programming Language :: Python :: 3.12
Classifier: Programming Language :: Python :: Implementation :: CPython
Classifier: Programming Language :: Python :: Implementation :: PyPy
Classifier: Topic :: Software Development
Classifier: Topic :: Software Development :: Libraries :: Python Modules
Classifier: Topic :: Security :: Cryptography
Requires-Python: >=3.12
License-File: LICENSE
